sphinxcontrib_robotdoc.py
sphinxcontrib_robotdoc-0.11.0.dist-info/METADATA
sphinxcontrib_robotdoc-0.11.0.dist-info/WHEEL
sphinxcontrib_robotdoc-0.11.0.dist-info/top_level.txt
sphinxcontrib_robotdoc-0.11.0.dist-info/RECORD
