Metadata-Version: 2.1
Name: sphinxcontrib-robotdoc
Version: 0.11.0
Summary: Sphinx extension to embed Robot Framework test cases and user keywords into Sphinx documents
Home-page: https://github.com/datakurre/sphinxcontrib-robotdoc/
Author: Asko Soukka
Author-email: asko.soukka@iki.fi
License: GPL
Platform: UNKNOWN
Classifier: Programming Language :: Python :: 2
Classifier: Programming Language :: Python :: 3
Requires-Dist: setuptools
Requires-Dist: sphinx
Requires-Dist: pygments (>=1.6rc1)
Requires-Dist: robotframework (>=2.7.1)
